examples/__init__.py
examples/minify/__init__.py
examples/minify/build.py
examples/minify/settings.py
examples/minify/static/css/common-min.css
examples/minify/static/css/common_multi-all.css
examples/minify/static/css/common_multi-min.css
examples/minify/static/css/common_url-min.css
examples/minify/static/css/test.css
examples/minify/static/css/test2.css
jingo_minify/__init__.py
jingo_minify/helpers.py
jingo_minify/tests.py
jingo_minify/utils.py
jingo_minify/bin/yuicompressor-2.4.7.jar
jingo_minify/management/__init__.py
jingo_minify/management/commands/__init__.py
jingo_minify/management/commands/compress_assets.py
jingo_minify-0.7.0.dist-info/DESCRIPTION.rst
jingo_minify-0.7.0.dist-info/METADATA
jingo_minify-0.7.0.dist-info/RECORD
jingo_minify-0.7.0.dist-info/WHEEL
jingo_minify-0.7.0.dist-info/metadata.json
jingo_minify-0.7.0.dist-info/top_level.txt
