Metadata-Version: 2.0
Name: jingo-minify
Version: 0.7.0
Summary: DEPRECATED - A Django app that will concat and minify JS and CSS.
Home-page: http://github.com/jsocol/jingo-minify
Author: Dave Dash, James Socol
Author-email: dd@mozilla.com, james@mozilla.com
License: BSD
Platform: UNKNOWN
Classifier: Development Status :: 4 - Beta
Classifier: Environment :: Web Environment
Classifier: Environment :: Web Environment :: Mozilla
Classifier: Intended Audience :: Developers
Classifier: Framework :: Django
Classifier: License :: OSI Approved :: BSD License
Classifier: Operating System :: OS Independent
Classifier: Programming Language :: Python
Classifier: Programming Language :: Python :: 2.7
Classifier: Topic :: Software Development :: Libraries :: Python Modules
Requires-Dist: jingo (>=0.8)
